oklahoma/__init__.py
oklahoma/__main__.py
oklahoma/api/__init__.py
oklahoma/api/routes_loader/__init__.py
oklahoma/auth/__init__.py
oklahoma/auth/auth0/__init__.py
oklahoma/auth/cognito/__init__.py
oklahoma/auth/firebase/__init__.py
oklahoma/auth/jwt/__init__.py
oklahoma/auth/keycloak/__init__.py
oklahoma/auth/ldap/__init__.py
oklahoma/aws/__init__.py
oklahoma/cli/__init__.py
oklahoma/cli/cli.py
oklahoma/db/__init__.py
oklahoma/db/base.py
oklahoma/db/database.py
oklahoma/environment/__init__.py
oklahoma/environment/_load_yaml.py
oklahoma/environment/_profile.py
oklahoma/environment/environment.py
oklahoma/exceptions/__init__.py
oklahoma/exceptions/statuscodes/__init__.py
oklahoma/fixtures/__init__.py
oklahoma/gcp/__init__.py
oklahoma/logger/__init__.py
oklahoma/mail/__init__.py
oklahoma/nosql/__init__.py
oklahoma/nosql/couch/__init__.py
oklahoma/nosql/elastic/__init__.py
oklahoma/nosql/mongo/__init__.py
oklahoma/py.typed
oklahoma/queues/__init__.py
oklahoma/queues/hazelcast/__init__.py
oklahoma/queues/kafka/__init__.py
oklahoma/queues/rabbit/__init__.py
oklahoma/settings/__init__.py
oklahoma/tasks/__init__.py
oklahoma/tasks/cron/__init__.py
oklahoma/tasks/docker/__init__.py
oklahoma/tasks/shell/__init__.py
oklahoma/tasks/ssh/__init__.py
oklahoma/tasks/watchfolder/__init__.py
oklahoma/utils/__init__.py
oklahoma/utils/singleton.py
oklahoma/utils/type_loader.py
oklahoma-0.1.0.dist-info/METADATA
oklahoma-0.1.0.dist-info/WHEEL
oklahoma-0.1.0.dist-info/RECORD
